[
	{
		"name": "$construct",
		"ident": 1,
		"order": 1,
		"pvardefs": [

		],
		"lvardefs": [
			{
				"name": "loFileUtils",
				"order": 1,
				"type": "kObject",
				"subtype": "ogFileUtils",
				"sublen": 0
			}
		]
	},
	{
		"name": "$destruct",
		"ident": 2,
		"order": 2,
		"pvardefs": [

		],
		"lvardefs": [

		]
	},
	{
		"name": "$setCSS",
		"ident": 7,
		"order": 3,
		"pvardefs": [
			{
				"name": "pcCSS",
				"order": 1,
				"type": "kCharacter",
				"subtype": "kSimplechar",
				"sublen": 100000000,
				"param": 1
			}
		],
		"lvardefs": [

		]
	},
	{
		"name": "$setInternalValue",
		"ident": 0,
		"order": 4,
		"pvardefs": [

		],
		"lvardefs": [
			{
				"name": "loFileUtils",
				"order": 1,
				"type": "kObject",
				"subtype": "ogFileUtils",
				"sublen": 0
			}
		]
	},
	{
		"name": "$setJavaScript",
		"ident": 6,
		"order": 5,
		"pvardefs": [
			{
				"name": "pcJavaScript",
				"order": 1,
				"type": "kCharacter",
				"subtype": "kSimplechar",
				"sublen": 100000000,
				"param": 1
			}
		],
		"lvardefs": [

		]
	},
	{
		"name": "$setTitle",
		"ident": 5,
		"order": 6,
		"pvardefs": [
			{
				"name": "pcText",
				"order": 1,
				"type": "kCharacter",
				"subtype": "kSimplechar",
				"sublen": 100000000,
				"param": 1
			}
		],
		"lvardefs": [

		]
	},
	{
		"name": "$_getStyleElement",
		"ident": 3,
		"order": 7,
		"pvardefs": [

		],
		"lvardefs": [
			{
				"name": "lcStyleElement",
				"order": 1,
				"type": "kCharacter",
				"subtype": "kSimplechar",
				"sublen": 100000000
			}
		]
	},
	{
		"name": "$_getScriptElement",
		"ident": 4,
		"order": 8,
		"pvardefs": [

		],
		"lvardefs": [
			{
				"name": "lcScriptElement",
				"order": 1,
				"type": "kCharacter",
				"subtype": "kSimplechar",
				"sublen": 100000000,
				"initval": "\"\""
			}
		]
	}
]
