{
	"classtype": "kSchema",
	"omnisversion": "11.0",
	"omnisbuild": 110035659,
	"internalversion": 9,
	"nextident": 32008,
	"properties": {
		"componenticon": 0,
		"componentinfo": {

		},
		"componenttype": "kCompStoreHidden",
		"createdate": "2016-07-10 10:58:53",
		"createinstancewhensubtype": true,
		"desc": "",
		"editor": "",
		"editordata": "",
		"external": true,
		"moddate": "2018-07-05 16:05:25",
		"servertablename": "",
		"showascheckedout": false,
		"userinfo": "",
		"vcsrevision": 0,
		"version": 1
	}
}
